pebblo/__init__.py
pebblo/utils.py
pebblo/app/__init__.py
pebblo/app/daemon.py
pebblo/app/api/__init__.py
pebblo/app/api/api.py
pebblo/app/api/local_ui_api.py
pebblo/app/api/redirection_api.py
pebblo/app/api/req_models.py
pebblo/app/api/v1.py
pebblo/app/config/__init__.py
pebblo/app/config/config.py
pebblo/app/config/models.py
pebblo/app/config/service.py
pebblo/app/config/utils.py
pebblo/app/enums/__init__.py
pebblo/app/enums/common.py
pebblo/app/enums/enums.py
pebblo/app/exceptions/__init__.py
pebblo/app/exceptions/exception_handler.py
pebblo/app/libs/__init__.py
pebblo/app/libs/responses.py
pebblo/app/models/__init__.py
pebblo/app/models/db_models.py
pebblo/app/models/db_response_models.py
pebblo/app/models/models.py
pebblo/app/models/sqltables.py
pebblo/app/pebblo-ui/index.html
pebblo/app/pebblo-ui/index.js
pebblo/app/pebblo-ui/src/app.js
pebblo/app/pebblo-ui/src/polyfill.js
pebblo/app/pebblo-ui/src/routes.js
pebblo/app/pebblo-ui/src/util.js
pebblo/app/pebblo-ui/src/components/Dialog.js
pebblo/app/pebblo-ui/src/components/IconButton.js
pebblo/app/pebblo-ui/src/components/accordion.js
pebblo/app/pebblo-ui/src/components/applicationList.js
pebblo/app/pebblo-ui/src/components/bubbleChart.js
pebblo/app/pebblo-ui/src/components/button.js
pebblo/app/pebblo-ui/src/components/card.js
pebblo/app/pebblo-ui/src/components/chartCard.js
pebblo/app/pebblo-ui/src/components/chips.js
pebblo/app/pebblo-ui/src/components/deleteApp.js
pebblo/app/pebblo-ui/src/components/emptyState.js
pebblo/app/pebblo-ui/src/components/findingsPanel.js
pebblo/app/pebblo-ui/src/components/header.js
pebblo/app/pebblo-ui/src/components/index.js
pebblo/app/pebblo-ui/src/components/keyValue.js
pebblo/app/pebblo-ui/src/components/legendBadge.js
pebblo/app/pebblo-ui/src/components/navbar.js
pebblo/app/pebblo-ui/src/components/progressBar.js
pebblo/app/pebblo-ui/src/components/retrievalDetails.js
pebblo/app/pebblo-ui/src/components/snippetDetails.js
pebblo/app/pebblo-ui/src/components/tab.js
pebblo-0.1.20.dist-info/LICENSE
pebblo-0.1.20.dist-info/METADATA
pebblo-0.1.20.dist-info/WHEEL
pebblo-0.1.20.dist-info/entry_points.txt
pebblo-0.1.20.dist-info/top_level.txt
pebblo-0.1.20.dist-info/RECORD
