Metadata-Version: 2.1
Name: pebblo
Version: 0.1.20
Summary: Pebblo Gen-AI Data Analyzer
Author-email: Pebblo Authors <pebblo@daxa.ai>
Maintainer-email: Pebblo Maintainer <pebblo@daxa.ai>
Project-URL: Homepage, https://github.com/daxa-ai/pebblo
Project-URL: Bug Reports, https://github.com/daxa-ai/pebblo/issues
Project-URL: Funding, https://donate.pypi.org
Project-URL: Source, https://github.com/daxa-ai/pebblo/
Keywords: langchain,ai,rag
Classifier: Development Status :: 3 - Alpha
Classifier: Intended Audience :: Developers
Classifier: Topic :: Software Development :: Build Tools
Classifier: License :: Other/Proprietary License
Classifier: Operating System :: OS Independent
Classifier: Programming Language :: Python :: 3
Classifier: Programming Language :: Python :: 3.9
Classifier: Programming Language :: Python :: 3.10
Classifier: Programming Language :: Python :: 3.11
Classifier: Programming Language :: Python :: 3.12
Requires-Python: >=3.9
License-File: LICENSE
Requires-Dist: fastapi==0.109.1
Requires-Dist: uvicorn==0.25.0
Requires-Dist: pydantic==2.8.2
Requires-Dist: pydantic-settings==2.4.0
Requires-Dist: presidio-analyzer==2.2.351
Requires-Dist: presidio-anonymizer==2.2.351
Requires-Dist: torch>=2.1.2
Requires-Dist: transformers==4.38.0
Requires-Dist: jinja2>=3.1.3
Requires-Dist: tqdm
Requires-Dist: xhtml2pdf==0.2.15
Requires-Dist: python-bidi==0.4.2
Requires-Dist: python-dateutil==2.9.0
Requires-Dist: sqlalchemy==2.0.32
Provides-Extra: dev
Requires-Dist: check-manifest; extra == "dev"
Provides-Extra: test
Requires-Dist: ruff; extra == "test"
